whither/app.py
whither/bridge.py
whither/whither.yml
whither/base/config_loader.py
whither/base/data.py
whither/base/metaclasses.py
whither/base/objects.py
whither/toolkits/bootstrap.py
whither/toolkits/gtk/application.py
whither/toolkits/gtk/web_container.py
whither/toolkits/gtk/window.py
whither/toolkits/qt/application.py
whither/toolkits/qt/bridge.py
whither/toolkits/qt/devtools.py
whither/toolkits/qt/interceptor.py
whither/toolkits/qt/web_container.py
whither/toolkits/qt/window.py
whither-0.3.2.dist-info/DESCRIPTION.rst
whither-0.3.2.dist-info/METADATA
whither-0.3.2.dist-info/RECORD
whither-0.3.2.dist-info/WHEEL
whither-0.3.2.dist-info/metadata.json
whither-0.3.2.dist-info/top_level.txt
