Metadata-Version: 2.0
Name: whither
Version: 0.3.2
Summary: Desktop application SDK for creating Universal Linux Applications.
Home-page: https://github.com/antergos/whither
Author: Antergos Linux Project
Author-email: dustin@antergos.com
License: GPL-3.0
Keywords: desktop-application-sdk framework sdk javascript universal html5
Platform: UNKNOWN
Classifier: Development Status :: 5 - Production/Stable
Classifier: Environment :: X11 Applications
Classifier: Intended Audience :: Developers
Classifier: License :: OSI Approved :: GNU General Public License v3 (GPLv3)
Classifier: Operating System :: POSIX :: Linux
Classifier: Programming Language :: JavaScript
Classifier: Programming Language :: Python :: 3.4
Classifier: Programming Language :: Python :: 3.5
Classifier: Programming Language :: Python :: 3.6
Classifier: Topic :: Software Development
Classifier: Topic :: Software Development :: Libraries :: Application Frameworks
Classifier: Topic :: Software Development :: Libraries :: Python Modules
Classifier: Topic :: Software Development :: User Interfaces
Requires-Dist: PyQt5
Requires-Dist: ruamel.yaml
